Workbook

Sheet Datos
A1: Participante | B1: Rol | C1: Funcionalidad más importante | D1: Ventas/día | E1: ¿Factura electrónica? | G1: Integrantes
A2: Carlos R. | B2: Dueño | C2: Control de inventario | D2: 50 | E2: Sí | G2: Juan Pablo Chacon Barragan
A3: Martha R. | B3: Cajera | C3: Registro de ventas | D3: 50 | E3: No sé | G3: Juan Sebastián Medina Cardozo
A4: Julián P. | B4: Empleado | C4: Registro de ventas | D4: 50 | E4: No me importa | G4: John Stiven Alba Quiroga
A5: Cliente 1 | B5: Cliente | C5: Ver precios en pantalla | D5: 0 | E5: Sí
A6: Cliente 2 | B6: Cliente | C6: Pago con tarjeta | D6: 0 | E6: Sí

Sheet Analisis
A2: Funcionalidad | B2: Conteo | C2: Frecuencia % | D2: Interpretación | F2: Métrica | G2: Valor | H2: Interpretación | K2: Respuesta | L2: Conteo
A3: Registro de ventas | B3: =COUNTIF(Datos!$C$2:$C$6,A3) | C3: =B3/COUNTA(Datos!$C$2:$C$6) | D3: Función más prioritaria del sistema. | F3: Promedio | G3: =AVERAGE(Datos!$D$2:$D$6) | H3: El sistema debe soportar una carga promedio cercana a 30 ventas/día considerando clientes no vendedores. | K3: Sí | L3: =COUNTIF(Datos!$E$2:$E$6,K3)
A4: Control de inventario | B4: =COUNTIF(Datos!$C$2:$C$6,A4) | C4: =B4/COUNTA(Datos!$C$2:$C$6) | D4: Necesidad crítica para evitar faltantes. | F4: Mínimo | G4: =MIN(Datos!$D$2:$D$6) | H4: Hay registros con 0 porque los clientes no reportan ventas propias. | K4: No sé | L4: =COUNTIF(Datos!$E$2:$E$6,K4)
A5: Ver precios en pantalla | B5: =COUNTIF(Datos!$C$2:$C$6,A5) | C5: =B5/COUNTA(Datos!$C$2:$C$6) | D5: Reduce tiempo de atención. | F5: Máximo | G5: =MAX(Datos!$D$2:$D$6) | H5: Se deben soportar jornadas de 50 ventas o más. | K5: No me importa | L5: =COUNTIF(Datos!$E$2:$E$6,K5)
A6: Pago con tarjeta | B6: =COUNTIF(Datos!$C$2:$C$6,A6) | C6: =B6/COUNTA(Datos!$C$2:$C$6) | D6: Mejora la experiencia de compra. | F6: Moda | G6: =MODE.SNGL(Datos!$D$2:$D$6) | H6: El valor más repetido es 50, indicando estabilidad en el caso base.
F9: Requisito | G9: Importancia | H9: Urgencia | I9: Prioridad
A10: Conclusión del análisis | F10: Registro de ventas | G10: 5 | H10: 5 | I10: =G10*H10
A11: Los módulos prioritarios del sistema son ventas, inventario, usuarios, consulta de precios y reportes, porque concentran la mayor frecuencia de mención y el mayor puntaje en la matriz. | F11: Control de inventario | G11: 5 | H11: 4 | I11: =G11*H11
F12: Gestión de usuarios | G12: 4 | H12: 4 | I12: =G12*H12
F13: Factura electrónica | G13: 3 | H13: 3 | I13: =G13*H13
F14: Pago con tarjeta | G14: 4 | H14: 3 | I14: =G14*H14
F15: Consulta de precios | G15: 4 | H15: 4 | I15: =G15*H15

Sheet Requisitos
A1: ID | B1: Descripción | C1: Tipo | D1: Fuente | E1: Prioridad | F1: Módulo | H1: Integrantes
A2: RF-01 | B2: El sistema debe permitir registrar ventas diarias de forma rápida. | C2: Funcional | D2: Encuesta + análisis | E2: Alta | F2: Ventas | H2: Juan Pablo Chacon Barragan
A3: RF-02 | B3: El sistema debe controlar entradas y salidas de inventario. | C3: Funcional | D3: Encuesta + entrevista | E3: Alta | F3: Inventario | H3: Juan Sebastián Medina Cardozo
A4: RF-03 | B4: El sistema debe mostrar precios de productos al cliente. | C4: Funcional | D4: Encuesta | E4: Media | F4: Ventas | H4: John Stiven Alba Quiroga
A5: RF-04 | B5: El sistema debe permitir registrar pagos con tarjeta. | C5: Funcional | D5: Encuesta | E5: Media | F5: Caja
A6: RF-05 | B6: El sistema debe generar reportes diarios de cierre de caja. | C6: Funcional | D6: Observación + análisis | E6: Alta | F6: Reportes
A7: RF-06 | B7: El sistema debe administrar un catálogo de productos con precio, categoría y stock mínimo. | C7: Funcional | D7: Revisión documental | E7: Alta | F7: Productos
A8: RF-07 | B8: El sistema debe permitir crear y gestionar usuarios con roles. | C8: Funcional | D8: Entrevista + taller | E8: Alta | F8: Usuarios
A9: RF-08 | B9: El sistema debe emitir comprobante o recibo de venta. | C9: Funcional | D9: Observación directa | E9: Media | F9: Ventas
A10: RNF-01 | B10: La interfaz debe ser simple y fácil de aprender. | C10: No funcional | D10: Entrevista simulada | E10: Alta | F10: General
A11: RN-01 | B11: Reducir pérdidas por falta de control de inventario. | C11: Negocio | D11: Análisis del negocio | E11: Alta | F11: Negocio
